featselection/__init__.py
featselection/filter.py
featselection-0.2.dev0.dist-info/LICENSE
featselection-0.2.dev0.dist-info/METADATA
featselection-0.2.dev0.dist-info/WHEEL
featselection-0.2.dev0.dist-info/top_level.txt
featselection-0.2.dev0.dist-info/RECORD
