Metadata-Version: 2.1
Name: featselection
Version: 0.2.dev0
Summary: Feature selection methods for Text Classification
Home-page: https://github.com/rcpf/featselection
Author: Rogério C. P. Fragoso
Author-email: rcpf@cin.ufpe.br
Maintainer: Rogério C. P. Fragoso
Maintainer-email: rcpf@cin.ufpe.br
License: MIT
Platform: UNKNOWN
Classifier: Development Status :: 3 - Alpha
Classifier: Intended Audience :: Developers
Classifier: Intended Audience :: Science/Research
Classifier: License :: OSI Approved :: BSD License
Classifier: Programming Language :: Python :: 3
Classifier: Programming Language :: Python :: 3.5
Classifier: Programming Language :: Python :: 3.6
Classifier: Topic :: Scientific/Engineering :: Artificial Intelligence
Requires-Python: >=3
Requires-Dist: scikit-learn (>=0.19.0)
Requires-Dist: numpy (>=1.14.5)
Requires-Dist: pandas (>=0.23.3)
Requires-Dist: scipy (>=0.13.3)
